[{"iconClass":"fa-folder","objectID":"/categories/%D0%BE-%D0%BD%D0%B0%D1%81","title":"О нас","type":"category","url":"/categories/%D0%BE-%D0%BD%D0%B0%D1%81"},{"iconClass":"fa-user","objectID":"/author/infopb","title":"InfoPB","type":"author","url":"/author/infopb"},{"iconClass":"fa-tag","objectID":"/tags/diskussion","title":"Diskussion","type":"tag","url":"/tags/diskussion"},{"iconClass":"fa-tag","objectID":"/tags/ideas","title":"Ideas","type":"tag","url":"/tags/ideas"},{"iconClass":"fa-tag","objectID":"/tags/qa","title":"Qa","type":"tag","url":"/tags/qa"},{"iconClass":"fa-tag","objectID":"/tags/show-tell","title":"Show tell","type":"tag","url":"/tags/show-tell"},{"iconClass":"fa-tag","objectID":"/tags/support","title":"Support","type":"tag","url":"/tags/support"},{"author":"","categories":["About us"],"iconClass":"fa-camera","language":"en","objectID":"53f854930dea037943c04005b4a41798","tags":[],"title":"Main areas of activity","type":"gallery","url":"/gallery/main-branches/"},{"author":null,"categories":["о нас"],"iconClass":"fa-camera","language":"ru","objectID":"7e1bb1915b5067b564c36af1c7203bca","tags":[],"title":"Основные направления деятельности","type":"gallery","url":"/ru/gallery/main-branches/"},{"author":null,"categories":null,"iconClass":"fa-pencil-alt","language":"en","objectID":"af3a21571f6ef32cbd77f29a8acaab52","tags":["Support","Discussions","Q\u0026A","Ideas","Show and tell"],"title":"Support and Discussions","type":"article","url":"/article/support-and-discussions/"},{"author":"InfoPB","categories":null,"iconClass":"fa-pencil-alt","language":"ru","objectID":"0fa7ce2a54235525aedcbd926f1ba174","tags":["Support","Diskussion","Q\u0026A","Ideas","Show \u0026 Tell"],"title":"Техническая поддержка и обсуждение","type":"article","url":"/ru/article/support-and-discussions/"},{"author":null,"categories":null,"iconClass":"fa-pencil-alt","language":"en","objectID":"0d7c8d9e5cc2657082773ae9a40d4a52","tags":null,"title":"Archive Page","type":"archive","url":"/archive/"},{"author":null,"categories":null,"iconClass":"fa-pencil-alt","language":"ru","objectID":"f20f6f22922bd75a772321d3a858deed","tags":null,"title":"Архив","type":"archive","url":"/ru/archive/"}]